<?xml version="1.0" encoding="UTF-8"?>
<fop version="1.0">

  <!--
    java -cp ..\build\fop.jar;..\lib\commons-logging-1.1.jar;..\lib\commons-io-1.3.1.jar org.apache.fop.fonts.apps.TTFReader ..\..\..\fonts\msyh.ttf msyh-tmp.xml
    ..\..\..\xmlbeans\bin\xpretty -indent 2 msyh-tmp.xml > msyh.xml

    java -cp ..\build\fop.jar;..\lib\commons-logging-1.1.jar;..\lib\commons-io-1.3.1.jar org.apache.fop.fonts.apps.TTFReader ..\..\..\fonts\msyhbd.ttf msyhbd-tmp.xml
    ..\..\..\xmlbeans\bin\xpretty -indent 2 msyhbd-tmp.xml > msyhbd.xml

    rm -f *-tmp.xml
  -->

  <base>.</base>
  <font-base>.</font-base>

  <renderers>
    <renderer mime="application/pdf">
      <fonts>
        <font metrics-url="msyhbd.xml" kerning="yes" embed-url="msyhbd.ttf">
            <font-triplet name="simhei" style="normal" weight="normal"/>
            <font-triplet name="simhei" style="normal" weight="bold"/>
            <font-triplet name="simhei" style="italic" weight="normal"/>
            <font-triplet name="simhei" style="italic" weight="bold"/>
        </font>
        <font metrics-url="msyh.xml" kerning="yes" embed-url="msyh.ttf">
            <font-triplet name="simsun" style="normal" weight="normal"/>
            <font-triplet name="simsun" style="normal" weight="bold"/>
            <font-triplet name="simsun" style="italic" weight="normal"/>
            <font-triplet name="simsun" style="italic" weight="bold"/>
        </font>
      </fonts>
    </renderer>
  </renderers>
</fop>
